<?xml version="1.0" encoding="UTF-8"?>
<odoo>
    <record id="category_termination" model="ir.module.category">
        <field name="name">Termination</field>
    </record>
    
    <record id="group_hr_training_ceo" model="res.groups">
        <field name="name">CEO</field>
        <field name="category_id" ref="category_termination"/>
    </record>

    <record id="group_hr_training_dceo" model="res.groups">
        <field name="name">DCEO</field>
        <field name="category_id" ref="category_termination"/>
    </record>

    <record id="group_hr_training_department_director" model="res.groups">
        <field name="name">Director</field>
        <field name="category_id" ref="category_termination"/>
    </record>
</odoo>